homi_pipeline/HoMi.py
homi_pipeline/HoMi_cleanup.py
homi_pipeline/__init__.py
homi_pipeline/check_config.py
homi_pipeline/profile_setup.py
homi_pipeline/snake_utils.py
homi_pipeline/snakefile
homi_pipeline/conda_envs/bbmap.yaml
homi_pipeline/conda_envs/fastqc.yaml
homi_pipeline/conda_envs/featureCounts.yaml
homi_pipeline/conda_envs/hisat2.yaml
homi_pipeline/conda_envs/hostile.yaml
homi_pipeline/conda_envs/humann.yaml
homi_pipeline/conda_envs/kraken.yaml
homi_pipeline/conda_envs/nonpareil.yaml
homi_pipeline/conda_envs/r_env.yaml
homi_pipeline/conda_envs/seqtk.yaml
homi_pipeline/conda_envs/trimmomatic.yaml
homi_pipeline/data/adapters.fa
homi_pipeline/rule_utils/Gut_metabolic_modules.Rmd
homi_pipeline/rule_utils/HUMAnN_microshades.Rmd
homi_pipeline/rule_utils/HUMAnN_to_phyloseq_helper.R
homi_pipeline/rule_utils/Kraken_microshades.Rmd
homi_pipeline/rule_utils/Metaphlan_microshades.Rmd
homi_pipeline/rule_utils/R_packages.R
homi_pipeline/rule_utils/aggregate_metaphlan_bugslists.py
homi_pipeline/rule_utils/bracken_to_phyloseq_helper.R
homi_pipeline/rule_utils/combine_kreports.py
homi_pipeline/rule_utils/convert_mphlan_v4_to_v3.py
homi_pipeline/rule_utils/counts_to_tpm.py
homi_pipeline/rule_utils/metaphlan_to_phyloseq_helper.R
homi_pipeline/rule_utils/nonpareil_curves.Rmd
homi_pipeline/rule_utils/read_reports.py
homi_pipeline/rule_utils/sam2bam.sh
homi_pipeline-1.0.13.data/scripts/HoMi.py
homi_pipeline-1.0.13.data/scripts/HoMi_cleanup.py
homi_pipeline-1.0.13.data/scripts/aggregate_metaphlan_bugslists.py
homi_pipeline-1.0.13.data/scripts/check_config.py
homi_pipeline-1.0.13.data/scripts/combine_kreports.py
homi_pipeline-1.0.13.data/scripts/convert_mphlan_v4_to_v3.py
homi_pipeline-1.0.13.data/scripts/counts_to_tpm.py
homi_pipeline-1.0.13.data/scripts/profile_setup.py
homi_pipeline-1.0.13.data/scripts/read_reports.py
homi_pipeline-1.0.13.data/scripts/snake_utils.py
homi_pipeline-1.0.13.dist-info/licenses/LICENSE
homi_pipeline-1.0.13.dist-info/METADATA
homi_pipeline-1.0.13.dist-info/WHEEL
homi_pipeline-1.0.13.dist-info/top_level.txt
homi_pipeline-1.0.13.dist-info/RECORD
