Metadata-Version: 2.4
Name: homi-pipeline
Version: 1.0.13
Summary: Pipeline for analysis of host-microbiome dual transcriptome data
Home-page: https://github.com/sterrettJD/HoMi
Download-URL: https://github.com/sterrettJD/HoMi/tarball/1.0.13
Author: John Sterrett
Author-email: john.sterrett@colorado.edu
Requires-Python: <3.12.0
License-File: LICENSE
Requires-Dist: snakemake<8.0.0
Requires-Dist: pulp==2.7.0
Requires-Dist: pandas
Requires-Dist: numpy
Requires-Dist: biopython
Requires-Dist: argparse
Requires-Dist: pyyaml
Requires-Dist: cookiecutter
Dynamic: author
Dynamic: author-email
Dynamic: description
Dynamic: description-content-type
Dynamic: download-url
Dynamic: home-page
Dynamic: license-file
Dynamic: requires-dist
Dynamic: requires-python
Dynamic: summary
